README.md
setup.py
bin/picluster
bin/piclusterdeamon
bin/sethostname
piClusterManager/__init__.py
piClusterManager/config.py
piClusterManager.egg-info/PKG-INFO
piClusterManager.egg-info/SOURCES.txt
piClusterManager.egg-info/dependency_links.txt
piClusterManager.egg-info/requires.txt
piClusterManager.egg-info/top_level.txt
piClusterManager/protocol/__init__.py
piClusterManager/protocol/agent.py
piClusterManager/protocol/node_finder.py
piClusterManager/protocol/node_manager.py