Metadata-Version: 2.1
Name: piClusterManager
Version: 0.1.6
Summary: Open Source Pi Clusters manager
Home-page: https://github.com/Lukas0025/piClusterManager
Author: Lukáš Plevač
Author-email: lukasplevac@gmail.com
License: UNKNOWN
Platform: UNKNOWN
Classifier: Programming Language :: Python :: 3
Classifier: License :: OSI Approved :: Apache Software License
Classifier: Operating System :: OS Independent
Requires-Python: >=3.0
